[{"name": "krishauid", "value": "62dac0de84770f378f2caec02c4bed01987b4bde", "domain": ".krisha.kz", "path": "/", "expires": 1784155485, "httpOnly": true, "secure": true, "sameSite": "None"}, {"name": "krssid", "value": "p8s5h3f9v036pm803fd4pi724a", "domain": ".krisha.kz", "path": "/", "expires": 1752633885, "httpOnly": true, "secure": true, "sameSite": "None"}, {"name": "kumd", "value": "UbZNSYJRz2PYXGPOicImeTtyjwZSVHjJmY7u%2B09tAiawKfigwuDgOeObCqdm%2BO8iZLfusHqDnqnxhn8Q5YS5raUUAJkz9trSRH3DyJScgBaGjNo3LyAsk9mLnFKpE6oQjDHNi%2F0Fc8vuBlWNOQX8VQ%3D%3D", "domain": ".krisha.kz", "path": "/", "expires": 1752623084, "httpOnly": true, "secure": true, "sameSite": "None"}, {"name": "kraid", "value": "3f20f7df-1c2d-4c5c-b01f-341e9f77051e", "domain": ".krisha.kz", "path": "/", "expires": 1784155487, "httpOnly": false, "secure": false, "sameSite": "None"}, {"name": "tutorial", "value": "%7B%22companyDocs%22%3A%22viewed%22%7D", "domain": ".krisha.kz", "path": "/", "expires": -1, "httpOnly": false, "secure": false, "sameSite": "None"}, {"name": "_gid", "value": "GA1.2.1859400021.1752619487", "domain": ".krisha.kz", "path": "/", "expires": 1752705887, "httpOnly": false, "secure": false, "sameSite": "None"}, {"name": "_gcl_au", "value": "1.1.1577650790.1752619487", "domain": ".krisha.kz", "path": "/", "expires": 1760395487, "httpOnly": false, "secure": false, "sameSite": "None"}, {"name": "_ga", "value": "GA1.1.1836571220.1752619487", "domain": ".krisha.kz", "path": "/", "expires": 1787179487, "httpOnly": false, "secure": false, "sameSite": "None"}, {"name": "_ym_uid", "value": "1752619487938137540", "domain": ".krisha.kz", "path": "/", "expires": 1784155487, "httpOnly": false, "secure": false, "sameSite": "None"}, {"name": "_ym_d", "value": "1752619487", "domain": ".krisha.kz", "path": "/", "expires": 1784155487, "httpOnly": false, "secure": false, "sameSite": "None"}, {"name": "_gat", "value": "1", "domain": ".krisha.kz", "path": "/", "expires": 1752619547, "httpOnly": false, "secure": false, "sameSite": "None"}, {"name": "_ga_6YZLS7YDS7", "value": "GS2.1.s1752619487$o1$g0$t1752619487$j60$l0$h0", "domain": ".krisha.kz", "path": "/", "expires": 1787179487, "httpOnly": false, "secure": false, "sameSite": "None"}, {"name": "_ym_isad", "value": "2", "domain": ".krisha.kz", "path": "/", "expires": 1752691487, "httpOnly": false, "secure": false, "sameSite": "None"}, {"name": "_ym_visorc", "value": "b", "domain": ".krisha.kz", "path": "/", "expires": 1752621287, "httpOnly": false, "secure": false, "sameSite": "None"}, {"name": "kr_cdn_host", "value": "//cf-check.kcdn.online", "domain": ".krisha.kz", "path": "/", "expires": 1752623087, "httpOnly": false, "secure": false, "sameSite": "None"}]